LICENSE
README.md
setup.py
unilink/__init__.py
unilink.egg-info/PKG-INFO
unilink.egg-info/SOURCES.txt
unilink.egg-info/dependency_links.txt
unilink.egg-info/requires.txt
unilink.egg-info/top_level.txt